bankingapi/DKB.py
bankingapi/__init__.py
bankingapi/exceptions/ItemNotFoundError.py
bankingapi/exceptions/__init__.py
bankingapi/parser/__init__.py
bankingapi/parser/parserDKB.py
bankingapi-0.1.5.dist-info/LICENSE
bankingapi-0.1.5.dist-info/METADATA
bankingapi-0.1.5.dist-info/WHEEL
bankingapi-0.1.5.dist-info/top_level.txt
bankingapi-0.1.5.dist-info/RECORD
