Metadata-Version: 2.1
Name: bankingapi
Version: 0.1.5
Summary: Banking API
Home-page: http://github.com/IJustDev/BankingAPI
Author: ijustdev
Author-email: alexanderpanovi@yahoo.de
License: MIT
Platform: UNKNOWN
Requires-Dist: selenium
